nomnivore/__init__.py
nomnivore/mssql.py
nomnivore-1.0.4.dist-info/licenses/LICENSE
nomnivore-1.0.4.dist-info/METADATA
nomnivore-1.0.4.dist-info/WHEEL
nomnivore-1.0.4.dist-info/top_level.txt
nomnivore-1.0.4.dist-info/RECORD
